setup.py
qtodotxt2/__init__.py
qtodotxt2/app.py
qtodotxt2/compile_rc.py
qtodotxt2/filters_controller.py
qtodotxt2/main_controller.py
qtodotxt2/qTodoTxt_style_rc.py
qtodotxt2.egg-info/PKG-INFO
qtodotxt2.egg-info/SOURCES.txt
qtodotxt2.egg-info/dependency_links.txt
qtodotxt2.egg-info/entry_points.txt
qtodotxt2.egg-info/requires.txt
qtodotxt2.egg-info/top_level.txt
qtodotxt2/controllers/__init__.py
qtodotxt2/lib/__init__.py
qtodotxt2/lib/file.py
qtodotxt2/lib/filters.py
qtodotxt2/lib/task_htmlizer.py
qtodotxt2/lib/tasklib.py
qtodotxt2/lib/tendo_singleton.py
qtodotxt2/qml/AboutBox.qml
qtodotxt2/qml/Actions.qml
qtodotxt2/qml/CompletionPopup.qml
qtodotxt2/qml/FilterView.qml
qtodotxt2/qml/MainMenu.qml
qtodotxt2/qml/MainToolBar.qml
qtodotxt2/qml/Preferences.qml
qtodotxt2/qml/QTodoTxt.qml
qtodotxt2/qml/TaskLine.qml
qtodotxt2/qml/TaskListView.qml
qtodotxt2/qml/ToolBarSeparator.qml
qtodotxt2/qml/Theme/Theme.qml
qtodotxt2/qml/Theme/qmldir
tests/__init__.py
tests/test_controller.py
tests/test_file.py
tests/test_htmlizer.py
tests/test_tasks.py